{
	"key": "db5fe957f15639c8b83003fc",
	"addrs": [
		{
			"addr": {
				"id": "56799b744758e6643b6378b869d8970c392bebab",
				"ip": "127.0.0.1",
				"port": 26616
			},
			"src": {
				"id": "912202a5d7853d5b578a2304b48024dde6c2ece9",
				"ip": "0.0.0.0",
				"port": 26636
			},
			"buckets": [
				188
			],
			"attempts": 1,
			"bucket_type": 1,
			"last_attempt": "2026-07-05T23:01:41.470205436+07:00",
			"last_success": "0001-01-01T00:00:00Z",
			"last_ban_time": "0001-01-01T00:00:00Z"
		},
		{
			"addr": {
				"id": "ce55f18b63b10bc3900fa20c3cbe79920ea22f02",
				"ip": "127.0.0.1",
				"port": 26626
			},
			"src": {
				"id": "912202a5d7853d5b578a2304b48024dde6c2ece9",
				"ip": "0.0.0.0",
				"port": 26636
			},
			"buckets": [
				188
			],
			"attempts": 0,
			"bucket_type": 1,
			"last_attempt": "2026-07-05T22:54:35.207034798+07:00",
			"last_success": "0001-01-01T00:00:00Z",
			"last_ban_time": "0001-01-01T00:00:00Z"
		}
	]
}